cuequivariance_jax/VERSION
cuequivariance_jax/__init__.py
cuequivariance_jax/activation.py
cuequivariance_jax/benchmarking.py
cuequivariance_jax/equivariant_polynomial.py
cuequivariance_jax/spherical_harmonics.py
cuequivariance_jax/experimental/__init__.py
cuequivariance_jax/experimental/indexed_linear.py
cuequivariance_jax/experimental/utils.py
cuequivariance_jax/flax_linen/__init__.py
cuequivariance_jax/flax_linen/layer_norm.py
cuequivariance_jax/rep_array/rep_array_.py
cuequivariance_jax/rep_array/rep_array_utils.py
cuequivariance_jax/rep_array/vmap.py
cuequivariance_jax/segmented_polynomials/indexing_mode.py
cuequivariance_jax/segmented_polynomials/segmented_polynomial.py
cuequivariance_jax/segmented_polynomials/segmented_polynomial_indexed_linear.py
cuequivariance_jax/segmented_polynomials/segmented_polynomial_naive.py
cuequivariance_jax/segmented_polynomials/segmented_polynomial_uniform_1d.py
cuequivariance_jax/segmented_polynomials/utils.py
cuequivariance_jax/triangle/__init__.py
cuequivariance_jax/triangle/_layer_norm_transpose.py
cuequivariance_jax/triangle/_naive_batching.py
cuequivariance_jax/triangle/_sigmoid_gated_dual_gemm.py
cuequivariance_jax/triangle/_triangle_attention.py
cuequivariance_jax/triangle/_triangle_multiplicative_update.py
cuequivariance_jax/triangle/_utils.py
Third_party_attr.txt
cuequivariance_jax-0.8.1.dist-info/METADATA
cuequivariance_jax-0.8.1.dist-info/WHEEL
cuequivariance_jax-0.8.1.dist-info/licenses/LICENSE
cuequivariance_jax-0.8.1.dist-info/RECORD
